imagenet1k.py
tinyimagenet.py
tinyimagenet-0.9.9.dist-info/LICENSE
tinyimagenet-0.9.9.dist-info/METADATA
tinyimagenet-0.9.9.dist-info/WHEEL
tinyimagenet-0.9.9.dist-info/top_level.txt
tinyimagenet-0.9.9.dist-info/zip-safe
tinyimagenet-0.9.9.dist-info/RECORD
