Metadata-Version: 2.1
Name: tinyimagenet
Version: 0.9.9
Summary: Dataset class for PyTorch and the TinyImageNet dataset, with automated download and extraction.
Home-page: https://github.com/facundoq/tinyimagenet
Author: Facundo Manuel Quiroga
Author-email: facundoq@gmail.com
Project-URL: Bug Tracker, https://github.com/facundoq/tinyimagenet/issues
Project-URL: Documentation, https://github.com/facundoq/tinyimagenet
Project-URL: Source Code, https://github.com/facundoq/tinyimagenet
Keywords: TinyImageNet ImageNet Dataset PyTorch torch torchvision
Classifier: License :: OSI Approved :: Python Software Foundation License
Classifier: License :: OSI Approved :: MIT License
Classifier: Development Status :: 4 - Beta
Classifier: Topic :: Scientific/Engineering :: Artificial Intelligence
Requires-Python: >=3.6
License-File: LICENSE
Requires-Dist: torchvision
